zenflow/__init__.py
zenflow/bijectors.py
zenflow/distributions.py
zenflow/flow.py
zenflow/layer_utils.py
zenflow/train.py
zenflow/utils.py
zenflow-0.2.2.dist-info/LICENSE
zenflow-0.2.2.dist-info/METADATA
zenflow-0.2.2.dist-info/WHEEL
zenflow-0.2.2.dist-info/top_level.txt
zenflow-0.2.2.dist-info/RECORD
