Metadata-Version: 2.2
Name: zenflow
Version: 0.2.2
Summary: Learn distributions with normalizing flows.
Author: Hans Dembinski
Author-email: hans.dembinski@gmail.com
Project-URL: repository, https://github.com/hdembinski/zenflow
Requires-Python: >=3.9
License-File: LICENSE
Requires-Dist: jax
Requires-Dist: jaxlib
Requires-Dist: flax
Requires-Dist: optax
Requires-Dist: typing_extensions
Provides-Extra: test
Requires-Dist: pytest; extra == "test"
Requires-Dist: pytest-cov; extra == "test"
Requires-Dist: coverage[toml]; extra == "test"
Requires-Dist: jacobi; extra == "test"
Provides-Extra: all
Requires-Dist: matplotlib; extra == "all"
Requires-Dist: scikit-learn; extra == "all"
Requires-Dist: numpy; extra == "all"
Requires-Dist: tqdm; extra == "all"
